MANIFEST.in
README.md
setup.py
mneme/__init__.py
mneme/auth.py
mneme/credentials.txt
mneme/manage.py
mneme/models.py
mneme/users.txt
mneme/views.py
mneme.egg-info/PKG-INFO
mneme.egg-info/SOURCES.txt
mneme.egg-info/dependency_links.txt
mneme.egg-info/entry_points.txt
mneme.egg-info/requires.txt
mneme.egg-info/top_level.txt
mneme/logs/__init__.py
mneme/static/darktile.jpg
mneme/static/lighttile.jpg
mneme/static/logo.svg
mneme/static/marked.js
mneme/static/nodes.js
mneme/static/style.css
mneme/templates/base.html
mneme/templates/mnemes/detail.html
mneme/templates/mnemes/list.html