Metadata-Version: 1.1
Name: mneme
Version: 0.1
Summary: A new and elegant note-taking format with a web viewer/editor.
Home-page: https://github.com/Risto-Stevcev/flask-mneme
Author: Risto Stevcev
Author-email: risto1@gmail.com
License: BSD
Keywords: note notes markdown json viewer editor text organizer
Platform: UNKNOWN
Classifier: Development Status :: 3 - Alpha
Classifier: Environment :: Web Environment
Classifier: Framework :: Flask
Classifier: Intended Audience :: Customer Service
Classifier: Intended Audience :: Developers
Classifier: Intended Audience :: Education
Classifier: Intended Audience :: End Users/Desktop
Classifier: Intended Audience :: Other Audience
Classifier: Intended Audience :: Science/Research
Classifier: License :: OSI Approved :: BSD License
Classifier: Natural Language :: English
Classifier: Operating System :: OS Independent
Classifier: Programming Language :: Python :: 2.7
Classifier: Topic :: Documentation
Classifier: Topic :: Education
Classifier: Topic :: Internet
Classifier: Topic :: Scientific/Engineering
Classifier: Topic :: Text Editors
Classifier: Topic :: Text Editors :: Documentation
Classifier: Topic :: Text Editors :: Text Processing
Classifier: Topic :: Text Processing :: Markup
Classifier: Topic :: Utilities
